LICENCE.md
LICENSE
README.md
setup.py
EnergyAlternativesPlaning/__init__.py
EnergyAlternativesPlaning/f_consumptionModels.py
EnergyAlternativesPlaning/f_graphicalTools.py
EnergyAlternativesPlaning/f_heat_pump.py
EnergyAlternativesPlaning/f_model_cost_functions.py
EnergyAlternativesPlaning/f_model_definition.py
EnergyAlternativesPlaning/f_model_operation_constraints.py
EnergyAlternativesPlaning/f_model_planing_constraints.py
EnergyAlternativesPlaning/f_multiRessourceModels.py
EnergyAlternativesPlaning/f_notebook.py
EnergyAlternativesPlaning/f_tools.py
EnergyAlternativesPlaning.egg-info/PKG-INFO
EnergyAlternativesPlaning.egg-info/SOURCES.txt
EnergyAlternativesPlaning.egg-info/dependency_links.txt
EnergyAlternativesPlaning.egg-info/requires.txt
EnergyAlternativesPlaning.egg-info/top_level.txt